odoo/addons/account_move_budget/README.rst
odoo/addons/account_move_budget/__init__.py
odoo/addons/account_move_budget/__manifest__.py
odoo/addons/account_move_budget/i18n/account_move_budget.pot
odoo/addons/account_move_budget/i18n/es.po
odoo/addons/account_move_budget/i18n/fr.po
odoo/addons/account_move_budget/i18n/it.po
odoo/addons/account_move_budget/models/__init__.py
odoo/addons/account_move_budget/models/account_move_budget.py
odoo/addons/account_move_budget/models/account_move_budget_line.py
odoo/addons/account_move_budget/readme/CONTRIBUTORS.md
odoo/addons/account_move_budget/readme/DESCRIPTION.md
odoo/addons/account_move_budget/readme/USAGE.md
odoo/addons/account_move_budget/security/ir.model.access.csv
odoo/addons/account_move_budget/static/description/icon.png
odoo/addons/account_move_budget/static/description/index.html
odoo/addons/account_move_budget/tests/__init__.py
odoo/addons/account_move_budget/tests/test_account_move_budget.py
odoo/addons/account_move_budget/views/account_move_budget_line_views.xml
odoo/addons/account_move_budget/views/account_move_budget_views.xml
odoo_addon_account_move_budget-17.0.1.0.0.7.dist-info/METADATA
odoo_addon_account_move_budget-17.0.1.0.0.7.dist-info/WHEEL
odoo_addon_account_move_budget-17.0.1.0.0.7.dist-info/top_level.txt
odoo_addon_account_move_budget-17.0.1.0.0.7.dist-info/RECORD
